ztshare/VERSION.txt
ztshare/__init__.py
ztshare/client.py
ztshare/data_pro.py
ztshare/common/__init__.py
ztshare/common/cons.py
ztshare/util/__init__.py
ztshare/util/str_util.py
ztshare/util/upass.py
ztshare-0.0.1.dist-info/LICENSE
ztshare-0.0.1.dist-info/METADATA
ztshare-0.0.1.dist-info/WHEEL
ztshare-0.0.1.dist-info/top_level.txt
ztshare-0.0.1.dist-info/RECORD
