Metadata-Version: 2.1
Name: ztshare
Version: 0.0.1
Summary: ztshare open platform interface package
Home-page: UNKNOWN
Author: zetta
Author-email: UNKNOWN
License: BSD
Keywords: Global Financial Data
Platform: UNKNOWN
Classifier: Development Status :: 4 - Beta
Classifier: Programming Language :: Python :: 3.2
Classifier: Programming Language :: Python :: 3.3
Classifier: Programming Language :: Python :: 3.4
Classifier: Programming Language :: Python :: 3.5
Classifier: Programming Language :: Python :: 3.8
Classifier: License :: OSI Approved :: BSD License
Requires-Dist: numpy (>=1.16.5)
Requires-Dist: pandas (>=1.0.0)
Requires-Dist: requests (>=2.0.0)
